{
  "placement" : {
    "average" : "cloud-1-0-0-1-0-0-0",
    "blobRead" : "cloud-1-1-0-0-0-1-1-1-0",
    "decisionTree" : "cloud-0-0-1-1-0",
    "errorEstimate" : "cloud-0-0-1-0-1-1",
    "mqttPublish" : "cloud-1-1-1-0-1-0-0-0-0",
    "multiVarLinearReg" : "cloud-0-0-1-1-1-1-0-0",
    "senMLParse" : "cloud-1-0-1-0-0-0-1-0-1",
    "sink" : "cloud-0-0-0-0-1-1-0-0",
    "source" : "cloud-1-1-1-0-0-1-0-1-0"
  },
  "appLoopLatency" : 39.93294950303002,
  "latencyPerTupleType" : {
    "blobRead_TUPLE" : 6.102252444444208,
    "average_TUPLE" : 5.242434243909425,
    "sink_TUPLE" : 1.1309772588322404,
    "errorEstimate_TUPLE" : 1.0961406138914978,
    "mqttPublish_TUPLE" : 2.5515153181920964,
    "decisionTree_TUPLE" : 2.8648196594647044,
    "multiVarLinearReg_TUPLE" : 16.219771890411074,
    "senMLParse_TUPLE" : 0.29270625656549626,
    "TUPLE" : 0.09714055555555677
  },
  "tuplesProcessedPerModule" : {
    "errorEstimate" : 14005,
    "average" : 4693,
    "multiVarLinearReg" : 9332,
    "decisionTree" : 9486,
    "sink" : 23250,
    "blobRead" : 4800,
    "source" : 4800,
    "senMLParse" : 4800,
    "mqttPublish" : 23272
  },
  "recsInPerModule" : {
    "errorEstimate" : 7.003196257771949,
    "average" : 2.4056913185471576,
    "multiVarLinearReg" : 4.747822779391206,
    "decisionTree" : 4.751627994593486,
    "sink" : 11.687434136805564,
    "blobRead" : 2.4127739228413145,
    "source" : 2.4220393470383756,
    "senMLParse" : 2.411804060455701,
    "mqttPublish" : 11.643576048459634
  },
  "recsOutPerModule" : {
    "errorEstimate" : 7.002700183855923,
    "average" : 2.3529693952334183,
    "multiVarLinearReg" : 4.673709166427293,
    "decisionTree" : 4.744780111375789,
    "sink" : 11.67920255617254,
    "blobRead" : 2.4054737497319034,
    "source" : 2.4220266164746502,
    "senMLParse" : 2.4116140379668267,
    "mqttPublish" : 11.640896309673842
  },
  "remainingDataPerDevice" : {
    "errorEstimate" : 110000,
    "average" : 20000,
    "multiVarLinearReg" : 20000,
    "decisionTree" : 300000,
    "sink" : 0,
    "blobRead" : 456000,
    "source" : 0,
    "senMLParse" : 0,
    "mqttPublish" : 44000
  },
  "executionTime" : 4368.0,
  "networkUsage" : 632706.36,
  "tuplesSentBySensors" : 4800
}