{
  "placement" : {
    "average" : "cloud-1-1-0-1-1-1-0-0",
    "blobRead" : "cloud-0-0-0-0-0-1-0-1-0",
    "decisionTree" : "cloud-0-0-0-0-0-0",
    "errorEstimate" : "cloud-0-0-0-1-1-1-0",
    "mqttPublish" : "cloud-1-0-0-0-0-1-1-0-0",
    "multiVarLinearReg" : "cloud-1-0-0-0-1-1-0-1-1",
    "senMLParse" : "cloud-0-0-1-0-1-0-1-0-1",
    "sink" : "cloud-0-1-0-1-1-0-0-1-1",
    "source" : "cloud-0-1-1-1-0"
  },
  "appLoopLatency" : 36.67173855856605,
  "latencyPerTupleType" : {
    "blobRead_TUPLE" : 0.19158769272731188,
    "average_TUPLE" : 2.7947368540888546,
    "sink_TUPLE" : 2.3732452418242733,
    "errorEstimate_TUPLE" : 0.4984233979147181,
    "mqttPublish_TUPLE" : 0.37117825111740216,
    "decisionTree_TUPLE" : 14.279470344952358,
    "multiVarLinearReg_TUPLE" : 1.2964192506382233,
    "senMLParse_TUPLE" : 4.248248964444426,
    "TUPLE" : 0.09365388888889459
  },
  "tuplesProcessedPerModule" : {
    "errorEstimate" : 14161,
    "average" : 4713,
    "multiVarLinearReg" : 9513,
    "decisionTree" : 9429,
    "sink" : 23289,
    "blobRead" : 4800,
    "source" : 4800,
    "senMLParse" : 4800,
    "mqttPublish" : 23316
  },
  "recsInPerModule" : {
    "errorEstimate" : 7.087457250203918,
    "average" : 2.4011532947374765,
    "multiVarLinearReg" : 4.803748478626624,
    "decisionTree" : 4.815072784444635,
    "sink" : 11.646119146357782,
    "blobRead" : 2.421793670178453,
    "source" : 2.4263244066499485,
    "senMLParse" : 2.419596258479371,
    "mqttPublish" : 11.659982958976915
  },
  "recsOutPerModule" : {
    "errorEstimate" : 7.080957680596446,
    "average" : 2.3627499291796257,
    "multiVarLinearReg" : 4.770776818310272,
    "decisionTree" : 4.729318580421614,
    "sink" : 11.644930227769732,
    "blobRead" : 2.421625208824031,
    "source" : 2.4263231290789795,
    "senMLParse" : 2.413960788980138,
    "mqttPublish" : 11.659369523235128
  },
  "remainingDataPerDevice" : {
    "errorEstimate" : 416000,
    "average" : 68000,
    "multiVarLinearReg" : 36000,
    "decisionTree" : 132000,
    "sink" : 0,
    "blobRead" : 0,
    "source" : 0,
    "senMLParse" : 0,
    "mqttPublish" : 54000
  },
  "executionTime" : 3628.0,
  "networkUsage" : 682929.3,
  "tuplesSentBySensors" : 4800
}