{
  "placement" : {
    "annotate" : "cloud-0-0-1-1-0-1-1-0-0-0",
    "azureTableInsert" : "cloud-1-0-0-1-0-1-0-1-0",
    "bloomFilter" : "cloud-0-1-1-0-1-1-1-0-0",
    "csvToSenML" : "cloud-1-1-1-0-0-0-0-0-1-0",
    "interpolation" : "cloud-1-0-1-1-1-1-1",
    "join" : "cloud-0-1-0-1-0-0-0-0-0-1",
    "mqttPublish" : "cloud-0-1-1-1-1-0-1-1-0-1",
    "rangeFilter" : "cloud-1-1-1-0-0-1-1-1",
    "senMLParse" : "cloud-0-0-1-0-1-1-0-1-0",
    "sink" : "cloud-1-0-1-0-1-0-1-0-0",
    "source" : "cloud-1-0-1-1-1-0-1-0-1-1"
  },
  "appLoopLatency" : 71.48280878787867,
  "latencyPerTupleType" : {
    "rangeFilter_TUPLE" : 0.2446569454544876,
    "join_TUPLE" : 0.8567774788209717,
    "bloomFilter_TUPLE" : 0.7077961450268556,
    "sink_TUPLE" : 0.18219971339458166,
    "interpolation_TUPLE" : 0.3951285896870534,
    "mqttPublish_TUPLE" : 0.2610851972730313,
    "csvToSenML_TUPLE" : 0.30310177793729115,
    "senMLParse_TUPLE" : 0.11075117575751596,
    "annotate_TUPLE" : 1.0768079432898408,
    "azureTableInsert_TUPLE" : 0.508990762997098,
    "TUPLE" : 0.09423717171716453
  },
  "tuplesProcessedPerModule" : {
    "bloomFilter" : 3288,
    "interpolation" : 1649,
    "azureTableInsert" : 1649,
    "sink" : 3284,
    "rangeFilter" : 4800,
    "annotate" : 1649,
    "source" : 4800,
    "join" : 1649,
    "senMLParse" : 4800,
    "mqttPublish" : 1649,
    "csvToSenML" : 1649
  },
  "recsInPerModule" : {
    "bloomFilter" : 1.6445284388801278,
    "interpolation" : 0.8437737223994493,
    "azureTableInsert" : 0.8308209347656593,
    "sink" : 1.6436648161674285,
    "rangeFilter" : 2.4009318709587433,
    "annotate" : 0.8353071417851886,
    "source" : 2.42106202912235,
    "join" : 0.8396935928406442,
    "senMLParse" : 2.410603159806919,
    "mqttPublish" : 0.8278326534506567,
    "csvToSenML" : 0.8310721887542827
  },
  "recsOutPerModule" : {
    "bloomFilter" : 1.6443070934087078,
    "interpolation" : 0.8433872878601513,
    "azureTableInsert" : 0.8304739945470693,
    "sink" : 1.6435397119543933,
    "rangeFilter" : 2.4007617509729062,
    "annotate" : 0.8346482874527772,
    "source" : 2.421059716332045,
    "join" : 0.8390900651244553,
    "senMLParse" : 2.410456884638084,
    "mqttPublish" : 0.8276699129388827,
    "csvToSenML" : 0.8308776443278016
  },
  "remainingDataPerDevice" : {
    "bloomFilter" : 25000,
    "interpolation" : 0,
    "azureTableInsert" : 0,
    "sink" : 0,
    "rangeFilter" : 515000,
    "annotate" : 0,
    "source" : 0,
    "join" : 0,
    "senMLParse" : 0,
    "mqttPublish" : 70000,
    "csvToSenML" : 0
  },
  "executionTime" : 672.0,
  "networkUsage" : 448356.23,
  "tuplesSentBySensors" : 4800
}