{
  "placement" : {
    "annotate" : "cloud-0-1-1-1-0-1-1-1",
    "azureTableInsert" : "cloud-1-0-1-0-1-0-0-1-1-1",
    "bloomFilter" : "cloud-1-1-0-1-0-1-1-1-0-0",
    "csvToSenML" : "cloud-1-0-0-0-1-1-1-1-1-0",
    "interpolation" : "cloud-1-1-0-0-1-1-1-0-0-0",
    "join" : "cloud-0-1-0-0-0-0-1-1-0-1",
    "mqttPublish" : "cloud-1-0-1-1-0-0-1-0-1-1",
    "rangeFilter" : "cloud-1-1-1-0-0-0",
    "senMLParse" : "cloud-1-0-1-1",
    "sink" : "cloud-0-0-1-1-1-0-1-0-0-1",
    "source" : "cloud-1-1-1-0-1-0-1-0-1-1"
  },
  "appLoopLatency" : 59.46399989393926,
  "latencyPerTupleType" : {
    "rangeFilter_TUPLE" : 16.32171391359592,
    "join_TUPLE" : 1.859982837092319,
    "bloomFilter_TUPLE" : 4.399922390521236,
    "sink_TUPLE" : 1.1789493114860556,
    "interpolation_TUPLE" : 3.331385243614898,
    "mqttPublish_TUPLE" : 1.1754814450998066,
    "csvToSenML_TUPLE" : 1.0784776348768865,
    "senMLParse_TUPLE" : 0.34440906000002175,
    "annotate_TUPLE" : 0.8981496697601001,
    "azureTableInsert_TUPLE" : 1.1762271748502626,
    "TUPLE" : 0.09398722222223023
  },
  "tuplesProcessedPerModule" : {
    "bloomFilter" : 3235,
    "interpolation" : 1553,
    "azureTableInsert" : 1548,
    "sink" : 3032,
    "rangeFilter" : 4722,
    "annotate" : 1548,
    "source" : 4800,
    "join" : 1548,
    "senMLParse" : 4800,
    "mqttPublish" : 1527,
    "csvToSenML" : 1548
  },
  "recsInPerModule" : {
    "bloomFilter" : 1.6223305659151315,
    "interpolation" : 0.7773854074502173,
    "azureTableInsert" : 0.7758530845776952,
    "sink" : 1.51827889575551,
    "rangeFilter" : 2.4141896889962906,
    "annotate" : 0.7798388288164361,
    "source" : 2.423017454307191,
    "join" : 0.7831888702603411,
    "senMLParse" : 2.417888647810997,
    "mqttPublish" : 0.7669532733909822,
    "csvToSenML" : 0.7763589455237129
  },
  "recsOutPerModule" : {
    "bloomFilter" : 1.6219950303671702,
    "interpolation" : 0.777224922024278,
    "azureTableInsert" : 0.7753891661241642,
    "sink" : 1.5173323033651733,
    "rangeFilter" : 2.3630738803080673,
    "annotate" : 0.7794871984029279,
    "source" : 2.4230149061268915,
    "join" : 0.7824407755175795,
    "senMLParse" : 2.4177161164533976,
    "mqttPublish" : 0.7664736646910675,
    "csvToSenML" : 0.7759330927359812
  },
  "remainingDataPerDevice" : {
    "bloomFilter" : 15000,
    "interpolation" : 25000,
    "azureTableInsert" : 105000,
    "sink" : 0,
    "rangeFilter" : 170000,
    "annotate" : 0,
    "source" : 0,
    "join" : 0,
    "senMLParse" : 0,
    "mqttPublish" : 110000,
    "csvToSenML" : 105000
  },
  "executionTime" : 868.0,
  "networkUsage" : 335889.36,
  "tuplesSentBySensors" : 4800
}