{
  "placement" : {
    "annotate" : "cloud-1-0-0-0-1-1-0-0-0-0",
    "azureTableInsert" : "cloud-0-1-1-1-0-0-1-0-1-0",
    "bloomFilter" : "cloud-0-0-1-0-0-0-1-0-1",
    "csvToSenML" : "cloud-1-1-1-0-1-1-0-0-0",
    "interpolation" : "cloud-1-0-1-1-1-0-0-1-1-1",
    "join" : "cloud-0-0-1-1-0-0-1-1",
    "mqttPublish" : "cloud-0-0-1-1-0-0-0-0-1-0",
    "rangeFilter" : "cloud-0-1-0-0-0-0-0-0-1-1",
    "senMLParse" : "cloud-0-0-0-1-0-1-1-0",
    "sink" : "cloud-1-0-1-0-0-1-0-1-1-0",
    "source" : "cloud-1-0-0-1-0-0-1-0-1"
  },
  "appLoopLatency" : 66.3161363333332,
  "latencyPerTupleType" : {
    "rangeFilter_TUPLE" : 1.609471873431991,
    "join_TUPLE" : 1.4434249736975473,
    "bloomFilter_TUPLE" : 4.4783998586854805,
    "sink_TUPLE" : 0.26170156624526464,
    "interpolation_TUPLE" : 0.5884634187081854,
    "mqttPublish_TUPLE" : 0.3976403808784237,
    "csvToSenML_TUPLE" : 0.9235745511176471,
    "senMLParse_TUPLE" : 0.17767796828285518,
    "annotate_TUPLE" : 1.7559577080939162,
    "azureTableInsert_TUPLE" : 0.8468174795886122,
    "TUPLE" : 0.09550138888888815
  },
  "tuplesProcessedPerModule" : {
    "bloomFilter" : 3259,
    "interpolation" : 1659,
    "azureTableInsert" : 1659,
    "sink" : 3262,
    "rangeFilter" : 4764,
    "annotate" : 1659,
    "source" : 4800,
    "join" : 1659,
    "senMLParse" : 4800,
    "mqttPublish" : 1631,
    "csvToSenML" : 1659
  },
  "recsInPerModule" : {
    "bloomFilter" : 1.6304762388503777,
    "interpolation" : 0.845620497350716,
    "azureTableInsert" : 0.8325156446100708,
    "sink" : 1.6330027603217039,
    "rangeFilter" : 2.4016330853354635,
    "annotate" : 0.8370181482239767,
    "source" : 2.420329558123458,
    "join" : 0.8415133972999626,
    "senMLParse" : 2.4102410634627374,
    "mqttPublish" : 0.8204579377949445,
    "csvToSenML" : 0.8331846364566533
  },
  "recsOutPerModule" : {
    "bloomFilter" : 1.6299760927648408,
    "interpolation" : 0.8452004546393882,
    "azureTableInsert" : 0.8319204301202081,
    "sink" : 1.632861412492479,
    "rangeFilter" : 2.3836208968265185,
    "annotate" : 0.8357461392011384,
    "source" : 2.4203282868578126,
    "join" : 0.840453428828729,
    "senMLParse" : 2.4100742054314086,
    "mqttPublish" : 0.820361959657405,
    "csvToSenML" : 0.8325330729937379
  },
  "remainingDataPerDevice" : {
    "bloomFilter" : 20000,
    "interpolation" : 0,
    "azureTableInsert" : 140000,
    "sink" : 0,
    "rangeFilter" : 330000,
    "annotate" : 0,
    "source" : 0,
    "join" : 0,
    "senMLParse" : 0,
    "mqttPublish" : 0,
    "csvToSenML" : 140000
  },
  "executionTime" : 672.0,
  "networkUsage" : 415114.27,
  "tuplesSentBySensors" : 4800
}