{
  "placement" : {
    "acc" : "cloud-1-1-0-0-0-1-1-1",
    "average" : "cloud-1-1-0-0-0-1-0-1-1",
    "blobUpload" : "cloud-0-1-0-1-1-0-0-0-0",
    "distinctCount" : "cloud-0-0-0-0-1-0-0-0",
    "kalmanFilter" : "cloud-1-1-0-1-0-0-0-1-0",
    "plt" : "cloud-1-1-1-1-1-1-0-0-0",
    "senMLParse" : "cloud-1-1-1-0-1-0-1-1-0",
    "sink" : "cloud-1-0-1-1-0-0-1-1-1",
    "slidingLinearReg" : "cloud-0-1-0-1-1-1-1-0-0",
    "source" : "cloud-0-0-0-1-0-1-0-0-0",
    "zip" : "cloud-1-0-1-0-1-0-0-0-1"
  },
  "appLoopLatency" : 72.31460704918408,
  "latencyPerTupleType" : {
    "average_TUPLE" : 0.8010280887930985,
    "sink_TUPLE" : 1.67636592814959,
    "acc_TUPLE" : 1.1407706804877504,
    "slidingLinearReg_TUPLE" : 16.014941329996695,
    "blobUpload_TUPLE" : 0.9457436578748509,
    "kalmanFilter_TUPLE" : 1.5411399759817825,
    "plt_TUPLE" : 0.9246218635238934,
    "zip_TUPLE" : 1.819377801292683,
    "senMLParse_TUPLE" : 3.1042222644444664,
    "distinctCount_TUPLE" : 1.7340713888278967,
    "TUPLE" : 0.09400833333333662
  },
  "tuplesProcessedPerModule" : {
    "acc" : 9764,
    "zip" : 9688,
    "average" : 4730,
    "distinctCount" : 4697,
    "blobUpload" : 9647,
    "sink" : 9556,
    "kalmanFilter" : 4719,
    "plt" : 9758,
    "slidingLinearReg" : 4650,
    "source" : 4800,
    "senMLParse" : 4800
  },
  "recsInPerModule" : {
    "acc" : 4.88433776331277,
    "zip" : 4.863958033775478,
    "average" : 2.366300044652958,
    "distinctCount" : 2.352116288041252,
    "blobUpload" : 4.842798394615193,
    "sink" : 4.791147106092464,
    "kalmanFilter" : 2.363116501052724,
    "plt" : 4.896884350833092,
    "slidingLinearReg" : 2.376729634782129,
    "source" : 2.4225283019439274,
    "senMLParse" : 2.410118782684957
  },
  "recsOutPerModule" : {
    "acc" : 4.883966200543923,
    "zip" : 4.859546090882133,
    "average" : 2.366083034482797,
    "distinctCount" : 2.348733627946789,
    "blobUpload" : 4.8414920378406245,
    "sink" : 4.790781804657134,
    "kalmanFilter" : 2.360344491329837,
    "plt" : 4.893057868203479,
    "slidingLinearReg" : 2.352679386102172,
    "source" : 2.4225257547923635,
    "senMLParse" : 2.405594309197737
  },
  "remainingDataPerDevice" : {
    "acc" : 12000,
    "zip" : 82000,
    "average" : 0,
    "distinctCount" : 94000,
    "blobUpload" : 455000,
    "sink" : 0,
    "kalmanFilter" : 138000,
    "plt" : 140000,
    "slidingLinearReg" : 0,
    "source" : 0,
    "senMLParse" : 480000
  },
  "executionTime" : 1544.0,
  "networkUsage" : 764604.31,
  "tuplesSentBySensors" : 4800
}