{
  "placement" : {
    "acc" : "cloud-1-0-1-1-1-0-0-0-1",
    "average" : "cloud-0-1-0-1-0-1-0-1-0",
    "blobUpload" : "cloud-0-1-0-1-0-0-0-0-1",
    "distinctCount" : "cloud-1-0-0-1-1-1-0-0-0",
    "kalmanFilter" : "cloud-1-0-1-1-0-1-0-1",
    "plt" : "cloud-0-0-0-0-0-0-0",
    "senMLParse" : "cloud-0-1-0-1-1-1-1-0",
    "sink" : "cloud-0-1-1-0-0-0-0-1-0",
    "slidingLinearReg" : "cloud-0-1-1-1-1-1-0-0-1",
    "source" : "cloud-1-0-1-1-1-0-1-0",
    "zip" : "cloud-1-0-0-0-1-0-0-1-0"
  },
  "appLoopLatency" : 70.59485776657448,
  "latencyPerTupleType" : {
    "average_TUPLE" : 3.378511507070784,
    "sink_TUPLE" : 11.63593009544137,
    "slidingLinearReg_TUPLE" : 6.383235612506099,
    "acc_TUPLE" : 0.960339962701919,
    "blobUpload_TUPLE" : 4.988228854807216,
    "kalmanFilter_TUPLE" : 11.252536436685517,
    "plt_TUPLE" : 17.3590766724885,
    "zip_TUPLE" : 2.0010902052117854,
    "senMLParse_TUPLE" : 0.2489579313130629,
    "distinctCount_TUPLE" : 4.362262553293072,
    "TUPLE" : 0.09434404040403825
  },
  "tuplesProcessedPerModule" : {
    "acc" : 9768,
    "zip" : 9635,
    "average" : 4800,
    "distinctCount" : 4701,
    "blobUpload" : 9533,
    "sink" : 9533,
    "kalmanFilter" : 4671,
    "plt" : 9635,
    "slidingLinearReg" : 4659,
    "source" : 4800,
    "senMLParse" : 4800
  },
  "recsInPerModule" : {
    "acc" : 4.885157217312323,
    "zip" : 4.85378793206577,
    "average" : 2.4070264096917384,
    "distinctCount" : 2.4025685968256205,
    "blobUpload" : 4.82601118615943,
    "sink" : 4.778547499538858,
    "kalmanFilter" : 2.403892176606736,
    "plt" : 4.929748166008461,
    "slidingLinearReg" : 2.3301104313120233,
    "source" : 2.4233844482332265,
    "senMLParse" : 2.4136312323417632
  },
  "recsOutPerModule" : {
    "acc" : 4.884594777493668,
    "zip" : 4.848353509911243,
    "average" : 2.402388272967871,
    "distinctCount" : 2.353015760848136,
    "blobUpload" : 4.799961387626255,
    "sink" : 4.77531601412625,
    "kalmanFilter" : 2.3404136457900293,
    "plt" : 4.870969749432161,
    "slidingLinearReg" : 2.3296685740414618,
    "source" : 2.4233798137785603,
    "senMLParse" : 2.4134409218348227
  },
  "remainingDataPerDevice" : {
    "acc" : 8000,
    "zip" : 0,
    "average" : 24000,
    "distinctCount" : 90000,
    "blobUpload" : 0,
    "sink" : 0,
    "kalmanFilter" : 22000,
    "plt" : 0,
    "slidingLinearReg" : 18000,
    "source" : 0,
    "senMLParse" : 0
  },
  "executionTime" : 2031.0,
  "networkUsage" : 659659.3,
  "tuplesSentBySensors" : 4800
}