{
  "placement" : {
    "acc" : "cloud-1-0-0-0-1-0",
    "average" : "cloud-0-1-1-0-0-0-0-0",
    "blobUpload" : "cloud-0-0-1-1-1-1-1-1-0",
    "distinctCount" : "cloud-1-1-1-1-1-1-1-1-0",
    "kalmanFilter" : "cloud-0-1-1-0-1-1-1-0",
    "plt" : "cloud-1-0-0-1-0-0-0-0",
    "senMLParse" : "cloud-1-1-1-1-1-1-0-1-1",
    "sink" : "cloud-0-1-0-1-1-0-0-0-1",
    "slidingLinearReg" : "cloud-1-1-1-1-0-0-0-0",
    "source" : "cloud-0-0-0-0-0-1-0",
    "zip" : "cloud-1-0-0-1-0-0-0-0-1"
  },
  "appLoopLatency" : 69.28714087245838,
  "latencyPerTupleType" : {
    "average_TUPLE" : 0.8751908965656374,
    "sink_TUPLE" : 5.760765230721612,
    "acc_TUPLE" : 0.5659318029336464,
    "slidingLinearReg_TUPLE" : 30.269634817100602,
    "blobUpload_TUPLE" : 14.124931288958845,
    "kalmanFilter_TUPLE" : 29.123986790845425,
    "plt_TUPLE" : 3.3819522299522204,
    "zip_TUPLE" : 2.385808601460843,
    "senMLParse_TUPLE" : 0.11261749090903309,
    "distinctCount_TUPLE" : 0.27004851090910664,
    "TUPLE" : 0.09262181818182183
  },
  "tuplesProcessedPerModule" : {
    "acc" : 9808,
    "zip" : 9759,
    "average" : 4800,
    "distinctCount" : 4800,
    "blobUpload" : 9501,
    "sink" : 9501,
    "kalmanFilter" : 4658,
    "plt" : 9783,
    "slidingLinearReg" : 4533,
    "source" : 4800,
    "senMLParse" : 4800
  },
  "recsInPerModule" : {
    "acc" : 4.9046472543337885,
    "zip" : 4.889007854339271,
    "average" : 2.404901501569453,
    "distinctCount" : 2.411667957945174,
    "blobUpload" : 4.849441321926245,
    "sink" : 4.789613063966592,
    "kalmanFilter" : 2.4039379601589275,
    "plt" : 4.902201194900501,
    "slidingLinearReg" : 2.3265517938585734,
    "source" : 2.424486097340086,
    "senMLParse" : 2.415333869115633
  },
  "recsOutPerModule" : {
    "acc" : 4.9043764561470296,
    "zip" : 4.87990459547784,
    "average" : 2.4035950706583016,
    "distinctCount" : 2.4114836932096515,
    "blobUpload" : 4.8092515056794065,
    "sink" : 4.788800129275601,
    "kalmanFilter" : 2.3358896961472833,
    "plt" : 4.892698866528423,
    "slidingLinearReg" : 2.3010296373812515,
    "source" : 2.4244837780032755,
    "senMLParse" : 2.415187019282968
  },
  "remainingDataPerDevice" : {
    "acc" : 12000,
    "zip" : 216000,
    "average" : 20000,
    "distinctCount" : 0,
    "blobUpload" : 0,
    "sink" : 0,
    "kalmanFilter" : 12000,
    "plt" : 10000,
    "slidingLinearReg" : 0,
    "source" : 0,
    "senMLParse" : 0
  },
  "executionTime" : 1827.0,
  "networkUsage" : 511529.46,
  "tuplesSentBySensors" : 4800
}