{
  "placement" : {
    "acc" : "cloud-1-1-0-1-1-1-1-0-1",
    "average" : "cloud-0-1-1-1-0-1-1-1-1",
    "blobUpload" : "cloud-1-0-1-1-1",
    "distinctCount" : "cloud-0-1-0-0-1-0-0-0-1",
    "kalmanFilter" : "cloud-0-0-0-1-1-1-1",
    "plt" : "cloud-1-0-0-1-0-0-0-1-1",
    "senMLParse" : "cloud-1-1-0-1-1-1-1-0-1-0",
    "sink" : "cloud-1-0-1-0-1-1-1-0",
    "slidingLinearReg" : "cloud-0-0-0-0-1-1-1-0-0",
    "source" : "cloud-0-1-0-0-0-0-0-1",
    "zip" : "cloud-0-1-0-1-1-1-1-0-1"
  },
  "appLoopLatency" : 77.92466398484433,
  "latencyPerTupleType" : {
    "average_TUPLE" : 2.525027103968392,
    "sink_TUPLE" : 9.000284007296097,
    "slidingLinearReg_TUPLE" : 3.701466029207792,
    "acc_TUPLE" : 0.7566554551056209,
    "blobUpload_TUPLE" : 15.243708336068156,
    "kalmanFilter_TUPLE" : 28.493109223116218,
    "plt_TUPLE" : 1.5338287834636184,
    "zip_TUPLE" : 2.7400920021177244,
    "senMLParse_TUPLE" : 0.21659650222224452,
    "distinctCount_TUPLE" : 3.416847890502673,
    "TUPLE" : 0.09764638888889489
  },
  "tuplesProcessedPerModule" : {
    "acc" : 9729,
    "zip" : 9608,
    "average" : 4729,
    "distinctCount" : 4713,
    "blobUpload" : 9596,
    "sink" : 9510,
    "kalmanFilter" : 4662,
    "plt" : 9608,
    "slidingLinearReg" : 4656,
    "source" : 4800,
    "senMLParse" : 4800
  },
  "recsInPerModule" : {
    "acc" : 4.8913117256316765,
    "zip" : 4.822265430121901,
    "average" : 2.399805064419692,
    "distinctCount" : 2.3986150257834464,
    "blobUpload" : 4.805491313785105,
    "sink" : 4.773977466871691,
    "kalmanFilter" : 2.4004526299480164,
    "plt" : 4.868187035448042,
    "slidingLinearReg" : 2.3290642879970096,
    "source" : 2.423017454307191,
    "senMLParse" : 2.4114519343949974
  },
  "recsOutPerModule" : {
    "acc" : 4.888249970241956,
    "zip" : 4.8209236371300825,
    "average" : 2.364800621731837,
    "distinctCount" : 2.356918639424113,
    "blobUpload" : 4.803512670639284,
    "sink" : 4.762034826448212,
    "kalmanFilter" : 2.3336825628552167,
    "plt" : 4.8431703025126644,
    "slidingLinearReg" : 2.328064283675033,
    "source" : 2.4228938737359758,
    "senMLParse" : 2.411305556204034
  },
  "remainingDataPerDevice" : {
    "acc" : 0,
    "zip" : 0,
    "average" : 20000,
    "distinctCount" : 126000,
    "blobUpload" : 430000,
    "sink" : 0,
    "kalmanFilter" : 8000,
    "plt" : 0,
    "slidingLinearReg" : 12000,
    "source" : 0,
    "senMLParse" : 8000
  },
  "executionTime" : 3499.0,
  "networkUsage" : 561401.68,
  "tuplesSentBySensors" : 4800
}