{
  "placement" : {
    "annotate" : "cloud-1-1",
    "azureTableInsert" : "cloud-0-0",
    "bloomFilter" : "cloud-1-1",
    "csvToSenML" : "cloud-1-0",
    "interpolation" : "cloud-0-0",
    "join" : "cloud-0",
    "mqttPublish" : "cloud-0-0",
    "rangeFilter" : "cloud-1-0",
    "senMLParse" : "cloud-0",
    "sink" : "cloud-0-0",
    "source" : "cloud-0-1"
  },
  "appLoopLatency" : 10.886726555555684,
  "latencyPerTupleType" : {
    "rangeFilter_TUPLE" : 0.6604586979172083,
    "join_TUPLE" : 1.0983552923461162,
    "bloomFilter_TUPLE" : 1.053050575343407,
    "sink_TUPLE" : 0.31666757427550507,
    "interpolation_TUPLE" : 1.5999808870010785,
    "mqttPublish_TUPLE" : 0.3552028310689403,
    "csvToSenML_TUPLE" : 1.8686417135419822,
    "senMLParse_TUPLE" : 2.2051786468101033,
    "annotate_TUPLE" : 1.8475688725091557,
    "azureTableInsert_TUPLE" : 0.6191550876361199,
    "TUPLE" : 0.11846093749997434
  },
  "tuplesProcessedPerModule" : {
    "bloomFilter" : 1429,
    "interpolation" : 736,
    "azureTableInsert" : 736,
    "sink" : 1472,
    "rangeFilter" : 2048,
    "annotate" : 736,
    "source" : 2048,
    "join" : 736,
    "senMLParse" : 2048,
    "mqttPublish" : 736,
    "csvToSenML" : 736
  },
  "recsInPerModule" : {
    "bloomFilter" : 0.7221851852854537,
    "interpolation" : 0.37145916606098806,
    "azureTableInsert" : 0.3702452880029968,
    "sink" : 0.7400403302305848,
    "rangeFilter" : 1.0358583787918978,
    "annotate" : 0.37070608298306934,
    "source" : 1.038374214247833,
    "join" : 0.3711957035571321,
    "senMLParse" : 1.0379258007345111,
    "mqttPublish" : 0.3701077729580031,
    "csvToSenML" : 0.37050622569841496
  },
  "recsOutPerModule" : {
    "bloomFilter" : 0.7219814642143496,
    "interpolation" : 0.3713642808711761,
    "azureTableInsert" : 0.3701636266953376,
    "sink" : 0.7399527534905409,
    "rangeFilter" : 1.0353805159163274,
    "annotate" : 0.3706368553846696,
    "source" : 1.038294152332911,
    "join" : 0.37094898501722295,
    "senMLParse" : 1.0363302301335429,
    "mqttPublish" : 0.3700387686215783,
    "csvToSenML" : 0.37042444925806023
  },
  "remainingDataPerDevice" : {
    "bloomFilter" : 0,
    "interpolation" : 0,
    "azureTableInsert" : 0,
    "sink" : 0,
    "rangeFilter" : 0,
    "annotate" : 0,
    "source" : 0,
    "join" : 0,
    "senMLParse" : 0,
    "mqttPublish" : 0,
    "csvToSenML" : 0
  },
  "executionTime" : 388.0,
  "networkUsage" : 21831.18,
  "tuplesSentBySensors" : 2048
}