{
  "placement" : {
    "average" : "cloud-0-1-0-0-1-0-1-1",
    "blobRead" : "cloud-0-1-1-0-1",
    "decisionTree" : "cloud-0-0-1-0-1-1-0-0-0-1",
    "errorEstimate" : "cloud-1-0-0-1-1-0-1-0-0",
    "mqttPublish" : "cloud-0-0-1-1-1-0-1-0-0-1",
    "multiVarLinearReg" : "cloud-0-0-1-1-0-1-1-1-0",
    "senMLParse" : "cloud-1-1-0-0-1-1-1-1-0-0",
    "sink" : "cloud-1-1-0-0-0-1-0-1-0",
    "source" : "cloud-1-1-0-0-1-0-0-0"
  },
  "appLoopLatency" : 35.66849612507222,
  "latencyPerTupleType" : {
    "blobRead_TUPLE" : 5.398115688888717,
    "average_TUPLE" : 5.379547246666619,
    "sink_TUPLE" : 2.8684050364777454,
    "errorEstimate_TUPLE" : 14.011067870878954,
    "mqttPublish_TUPLE" : 2.4692753547166486,
    "decisionTree_TUPLE" : 0.6303147922210572,
    "multiVarLinearReg_TUPLE" : 1.793334250503993,
    "senMLParse_TUPLE" : 0.11545688888876235,
    "TUPLE" : 0.09651499999999677
  },
  "tuplesProcessedPerModule" : {
    "errorEstimate" : 14051,
    "average" : 4800,
    "multiVarLinearReg" : 9600,
    "decisionTree" : 9600,
    "sink" : 23254,
    "blobRead" : 4800,
    "source" : 4800,
    "senMLParse" : 4800,
    "mqttPublish" : 23459
  },
  "recsInPerModule" : {
    "errorEstimate" : 7.106883007816277,
    "average" : 2.41214870776779,
    "multiVarLinearReg" : 4.812257284488486,
    "decisionTree" : 4.813222435440571,
    "sink" : 11.628641606424424,
    "blobRead" : 2.4180066375088205,
    "source" : 2.423506804247802,
    "senMLParse" : 2.421055656748163,
    "mqttPublish" : 11.730445068638977
  },
  "recsOutPerModule" : {
    "errorEstimate" : 7.026374972331578,
    "average" : 2.4061080267343202,
    "multiVarLinearReg" : 4.805583460342616,
    "decisionTree" : 4.8094396394793515,
    "sink" : 11.631743615031358,
    "blobRead" : 2.4119366180441797,
    "source" : 2.4235004312337116,
    "senMLParse" : 2.4209081103549543,
    "mqttPublish" : 11.729705793245072
  },
  "remainingDataPerDevice" : {
    "errorEstimate" : 196000,
    "average" : 188000,
    "multiVarLinearReg" : 188000,
    "decisionTree" : 188000,
    "sink" : 0,
    "blobRead" : 0,
    "source" : 0,
    "senMLParse" : 0,
    "mqttPublish" : 406000
  },
  "executionTime" : 4884.0,
  "networkUsage" : 735317.48,
  "tuplesSentBySensors" : 4800
}